{
	"id": [
		80466
	],
	"name": "Continental Explorer: Moonlit Isles (II)",
	"achievementGroupId": 66,
	"achievementGroupName": "Nod-Krai: An Elysium of Moonlight and Wanderings (II)",
	"sortOrder": 427,
	"stages": 1,
	"stage1": {
		"title": "Continental Explorer: Moonlit Isles (II)",
		"description": "Light up the maps of the following areas in Nod-Krai: Voidsea Outlook, Wavechaser Plain, and Ashveil Peak.",
		"progress": 1,
		"reward": {
			"id": 201,
			"name": "Primogem",
			"count": 5
		}
	}
}