{
	"id": [
		80469
	],
	"name": "Truy Vết Màn Đêm - Đảo Ánh Trăng II",
	"achievementGroupId": 66,
	"achievementGroupName": "Nod-Krai: Thiên Đường Của Ánh Trăng Và Kẻ Lang Bạt (II)",
	"sortOrder": 430,
	"stages": 1,
	"stage1": {
		"title": "Truy Vết Màn Đêm - Đảo Ánh Trăng II",
		"description": "Mở khóa tất cả phong ấn Vùng Đất Kho Báu Kuuhenki ở Trạm Gác Biển Hư Không, Đồng Bằng Đuổi Sóng và Đỉnh Tro Phủ thuộc khu vực Nod-Krai.",
		"progress": 3,
		"reward": {
			"id": 201,
			"name": "Nguyên Thạch",
			"count": 10
		}
	}
}