{
	"id": 20080501,
	"monsterId": 20080501,
	"name": "Aufkommende Strömung – Nachkomme der Frostnacht",
	"specialNames": [
		"Aufkommende Strömung"
	],
	"monsterType": "MONSTER_ORDINARY",
	"enemyType": "ELITE",
	"categoryType": "CODEX_SUBTYPE_ELEMENTAL",
	"categoryText": "Elementare Lebensformen",
	"description": "Ein elegantes Elementarwesen, das eine immense elementare Affinität besitzt. Über die langen Jahre war es hohen Konzentrationen der Hydro-Kraft ausgesetzt, was zu seiner heutigen Form führte.\nSein glasklarer Körper besteht fast ausschließlich aus reinsten Wassertropfen. Obwohl seine Natur sanfter ist als die der meisten seiner Artgenossen, sollte man nicht den Fehler begehen, ihn zu provozieren. Dann wird er nämlich das ihn umgebende Wasser augenblicklich in messerscharfe Klingen verwandeln, die mit der Abwehr des unvorsichtigen Eindringlings kurzen Prozess machen.\nIn den noch existierenden Gebeten des hohen Nordens wurden sie aus dem Segen des Frostmonds geboren und symbolisieren die reine Quelle und das erste Strahlen. Vielleicht ist das der Grund, warum sie die Befleckung ihrer blassen Reinheit mit den sieben Farben des himmlischen Lichts als unerträglich empfinden und deshalb alles Leben, das sich ihnen nähert, zurückweisen.",
	"rewardPreview": []
}