{
	"id": 10000125,
	"name": "Moonlit Mirage",
	"rarity": 3,
	"foodtype": "SPECIALTY",
	"filterType": "COOK_FOOD_DEFENSE",
	"filterText": "DEF-Boosting Dish",
	"effect": "Increases all party members' Max HP by 30% for 300s. In Co-Op Mode, this effect only applies to your own character(s).",
	"description": "Columbina's specialty. The translucent candy looks like droplets of dew gathered from moonlight. Its delicate sweetness flits in and out of reach, as if luring you into a beautiful, fleeting dream. You can't help but wonder at the skill and care that went into making it...",
	"baseDishId": 3608,
	"baseDishName": "Berry Herbal Candy",
	"characterId": 10000125,
	"characterName": "Columbina",
	"ingredients": [
		{
			"id": 101262,
			"name": "Nocturnal Blossom",
			"count": 2
		},
		{
			"id": 101268,
			"name": "Winter Icelea",
			"count": 2
		},
		{
			"id": 101265,
			"name": "Midsommar Berry",
			"count": 2
		},
		{
			"id": 101264,
			"name": "Lakkaberry",
			"count": 2
		}
	]
}