{
	"id": 10000125,
	"name": "Ảo Ảnh Ánh Trăng",
	"rarity": 3,
	"foodtype": "SPECIALTY",
	"filterType": "COOK_FOOD_DEFENSE",
	"filterText": "Món Dạng Phòng Ngự",
	"effect": "Giới hạn HP của toàn bộ nhân vật trong đội tăng 30% trong 300s. Trong chế độ nhiều người chơi, chỉ có hiệu lực với bản thân.",
	"description": "Món ăn độc quyền của Columbina. Những viên kẹo trong suốt như giọt sương đêm dưới ánh trăng, mang theo vị ngọt tinh tế khó nắm bắt, như thể được đưa vào một giấc mơ đẹp đẽ mà hư ảo. Làm thế nào cô ấy lại trải nghiệm được một cảm giác mới lạ và chưa từng có như vậy...?",
	"baseDishId": 3608,
	"baseDishName": "Kẹo Hoa Quả Thảo Mộc",
	"characterId": 10000125,
	"characterName": "Columbina",
	"ingredients": [
		{
			"id": 101262,
			"name": "Hoa Ảnh Đêm",
			"count": 2
		},
		{
			"id": 101268,
			"name": "Cỏ Đông Lăng",
			"count": 2
		},
		{
			"id": 101265,
			"name": "Quả Sồi Hè",
			"count": 2
		},
		{
			"id": 101264,
			"name": "Quả Lakka",
			"count": 2
		}
	]
}